signialib/__init__.py
signialib/_session_base.py
signialib/calibrations/001/Ferraris/2022-07-24_16-00/001_2022-01-10_10-48.json
signialib/calibrations/002/Ferraris/2022-07-24_16-00/002_2022-01-10_10-48.json
signialib/consts.py
signialib/dataset.py
signialib/datastream.py
signialib/exceptions.py
signialib/header.py
signialib/session.py
signialib-2.10.0.dist-info/LICENSE
signialib-2.10.0.dist-info/METADATA
signialib-2.10.0.dist-info/WHEEL
signialib-2.10.0.dist-info/RECORD
